img2gb/__init__.py
img2gb/__main__.py
img2gb/c_export.py
img2gb/cli.py
img2gb/gbtile.py
img2gb/gbtilemap.py
img2gb/gbtileset.py
img2gb/helpers.py
img2gb/version.py
img2gb-1.3.0.dist-info/LICENSE
img2gb-1.3.0.dist-info/METADATA
img2gb-1.3.0.dist-info/WHEEL
img2gb-1.3.0.dist-info/entry_points.txt
img2gb-1.3.0.dist-info/top_level.txt
img2gb-1.3.0.dist-info/RECORD
