Metadata-Version: 2.1
Name: img2gb
Version: 1.3.0
Summary: Converts images to GameBoy tileset
Home-page: https://github.com/flozz/img2gb
Author: Fabien LOISON
License: BSD-3-Clause
Project-URL: Source Code, https://github.com/flozz/img2gb
Project-URL: Issues, https://github.com/flozz/img2gb/issues
Project-URL: Chat, https://discord.gg/P77sWhuSs4
Project-URL: Donate, https://github.com/flozz/img2gb#support-this-project
Keywords: gb gameboy image tile tileset tilemap
License-File: LICENSE
Requires-Dist: pillow>=5.0.0
Provides-Extra: dev
Requires-Dist: nox; extra == "dev"
Requires-Dist: flake8; extra == "dev"
Requires-Dist: pytest; extra == "dev"
Requires-Dist: black; extra == "dev"
Requires-Dist: sphinx; extra == "dev"
Requires-Dist: sphinx-rtd-theme; extra == "dev"
